sbk/__init__.py
sbk/__main__.py
sbk/cli.py
sbk/cli_io.py
sbk/cli_util.py
sbk/ecc_rs.py
sbk/electrum_mnemonic.py
sbk/enc_util.py
sbk/gf.py
sbk/gf_lut.py
sbk/gf_poly.py
sbk/gf_util.py
sbk/kdf.py
sbk/mnemonic.py
sbk/params.py
sbk/primes.py
sbk/shamir.py
sbk/sys_info.py
sbk-2021.1001a0.dist-info/LICENSE
sbk-2021.1001a0.dist-info/METADATA
sbk-2021.1001a0.dist-info/WHEEL
sbk-2021.1001a0.dist-info/entry_points.txt
sbk-2021.1001a0.dist-info/top_level.txt
sbk-2021.1001a0.dist-info/zip-safe
sbk-2021.1001a0.dist-info/RECORD
