Metadata-Version: 2.1
Name: sbk
Version: 2021.1001a0
Summary: Wallet seed generation from a brainkey with Shamir Secret Shares as Backup.
Home-page: https://gitlab.com/mbarkhau/sbk
Author: Manuel Barkhau
Author-email: mbarkhau@gmail.com
License: MIT
Keywords: ssss shamir split share secret bitcoin electrum seed brainkey crypto
Platform: UNKNOWN
Classifier: Development Status :: 3 - Alpha
Classifier: Environment :: Console
Classifier: Environment :: Other Environment
Classifier: Intended Audience :: Developers
Classifier: License :: OSI Approved :: MIT License
Classifier: Operating System :: Unix
Classifier: Operating System :: POSIX
Classifier: Programming Language :: Python
Classifier: Programming Language :: Python :: 3.6
Classifier: Programming Language :: Python :: 3.7
Classifier: Programming Language :: Python :: Implementation :: CPython
Classifier: Programming Language :: Python :: Implementation :: PyPy
Classifier: Topic :: Software Development :: Libraries
Classifier: Topic :: Software Development :: Libraries :: Python Modules
Requires-Python: >=3.6
Requires-Dist: click (==7.0)
Requires-Dist: click-repl (==0.1.6)
Requires-Dist: pylev (==1.3.0)
Requires-Dist: argon2-cffi (==19.2.0)
